fluxutils/__init__.py
fluxutils/cli/__init__.py
fluxutils/cli/core.py
fluxutils/cli/decorators.py
fluxutils/cli/exceptions.py
fluxutils/cli/formatters.py
fluxutils/cli/parsers.py
fluxutils/cli/prompt.py
fluxutils/decorators/__init__.py
fluxutils/decorators/core.py
fluxutils/decorators/exceptions.py
fluxutils/log/__init__.py
fluxutils/log/core.py
fluxutils/log/handlers.py
fluxutils/log/template.py
fluxutils/log/utils.py
fluxutils/tests/cli/cli.py
fluxutils/tests/decorators/test1.py
fluxutils/tests/log/test1.py
fluxutils/tests/log/test2.py
fluxutils-1.2.0.1.dist-info/LICENSE
fluxutils-1.2.0.1.dist-info/METADATA
fluxutils-1.2.0.1.dist-info/WHEEL
fluxutils-1.2.0.1.dist-info/top_level.txt
fluxutils-1.2.0.1.dist-info/RECORD
