Metadata-Version: 2.1
Name: fluxutils
Version: 1.2.0.1
Summary: Various utilties to enhance your projects
Author: dombom
License: MIT License
Project-URL: Homepage, https://github.com/DomBom16/fluxutils
Keywords: utils,logger,log
Classifier: License :: OSI Approved :: MIT License
Classifier: Programming Language :: Python
Classifier: Programming Language :: Python :: 3
Requires-Python: >=3.12
License-File: LICENSE
Requires-Dist: black
Requires-Dist: pygments
Requires-Dist: colorama
